agm_dict_validator/__init__.py
agm_dict_validator/dict_validator.py
dict_validator/__init__.py
dict_validator/dict_validator.py
agm_dict_validator-0.0.1.dist-info/METADATA
agm_dict_validator-0.0.1.dist-info/WHEEL
agm_dict_validator-0.0.1.dist-info/top_level.txt
agm_dict_validator-0.0.1.dist-info/RECORD
