Metadata-Version: 2.1
Name: agm-dict-validator
Version: 0.0.1
Summary: Custom dict validator
Author-email: alexgeniusman@gmail.com
